bigc/__init__.py
bigc/api.py
bigc/api_client.py
bigc/data/__init__.py
bigc/data/order_status.py
bigc/exceptions.py
bigc/resources/__init__.py
bigc/resources/carts.py
bigc/resources/categories.py
bigc/resources/checkouts.py
bigc/resources/currencies.py
bigc/resources/customer_groups.py
bigc/resources/customers.py
bigc/resources/orders.py
bigc/resources/product_variants.py
bigc/resources/products.py
bigc/resources/webhooks.py
bigc/utils.py
bigc-0.2.16.dist-info/LICENSE.txt
bigc-0.2.16.dist-info/METADATA
bigc-0.2.16.dist-info/WHEEL
bigc-0.2.16.dist-info/RECORD
