Metadata-Version: 2.3
Name: bigc
Version: 0.2.16
Summary: Unofficial client for the BigCommerce API
License: MIT
Keywords: bigcommerce,api,client
Author: Ryan Thomson
Author-email: ryan@medshift.com
Requires-Python: >=3.9,<4.0
Classifier: Development Status :: 3 - Alpha
Classifier: Intended Audience :: Developers
Classifier: License :: OSI Approved :: MIT License
Classifier: Programming Language :: Python :: 3
Classifier: Programming Language :: Python :: 3.9
Classifier: Programming Language :: Python :: 3.10
Classifier: Programming Language :: Python :: 3.11
Classifier: Programming Language :: Python :: 3.12
Classifier: Programming Language :: Python :: 3.13
Classifier: Topic :: Software Development :: Libraries :: Python Modules
Requires-Dist: requests (>=2.27,<3.0)
Project-URL: Homepage, https://github.com/MedShift/bigc
Project-URL: Repository, https://github.com/MedShift/bigc.git
